{
  "title": "Avatar with Image",
  "description": "An Avatar component with an image incorporates a user or entity representation using a profile picture or image, adding a personalized touch and visual identification within a user interface.",
  "argTypes": {},
  "reactLive": {
    "Avatar": "@/components/ui/avatar",
    "AvatarBadge": "@/components/ui/avatar",
    "AvatarFallbackText": "@/components/ui/avatar",
    "AvatarImage": "@/components/ui/avatar",
    "Heading": "@/components/ui/heading",
    "HStack": "@/components/ui/hstack",
    "Text": "@/components/ui/text",
    "VStack": "@/components/ui/vstack"
  }
}
